eml_to_html.py
eml_to_html-0.0.2.data/scripts/eml_to_html.py
eml_to_html-0.0.2.dist-info/LICENSE
eml_to_html-0.0.2.dist-info/METADATA
eml_to_html-0.0.2.dist-info/WHEEL
eml_to_html-0.0.2.dist-info/entry_points.txt
eml_to_html-0.0.2.dist-info/top_level.txt
eml_to_html-0.0.2.dist-info/RECORD
