Metadata-Version: 2.1
Name: eml-to-html
Version: 0.0.2
Summary: Converts `.eml` files to HTML.
Home-page: https://github.com/dunnkers/eml-to-html
Author: Jeroen Overschie
Author-email: jeroen@darius.nl
Maintainer: Jeroen Overschie
Maintainer-email: jeroen@darius.nl
License: MIT
Project-URL: Github, https://github.com/dunnkers/eml-to-html
Project-URL: Bug Tracker, https://github.com/dunnkers/eml-to-html/issues
Project-URL: Documentation, https://dunnkers.com/eml-to-html
Platform: UNKNOWN
Classifier: License :: OSI Approved :: MIT License
Classifier: Development Status :: 4 - Beta
Classifier: Programming Language :: Python :: 3.7
Classifier: Programming Language :: Python :: 3.8
Classifier: Programming Language :: Python :: 3.9
Classifier: Programming Language :: Python :: 3.10
Classifier: Operating System :: POSIX :: Linux
Classifier: Operating System :: MacOS
Classifier: Operating System :: Microsoft :: Windows
Classifier: Typing :: Typed
Classifier: Topic :: Software Development
Classifier: Topic :: Software Development :: Libraries :: Python Modules
Requires-Python: >= 3.7
License-File: LICENSE
